MANIFEST.in
README.rst
chdkptp_module.diff
setup.py
chdkptp/__init__.py
chdkptp/device.py
chdkptp/lua.py
chdkptp/util.py
chdkptp.py.egg-info/PKG-INFO
chdkptp.py.egg-info/SOURCES.txt
chdkptp.py.egg-info/dependency_links.txt
chdkptp.py.egg-info/requires.txt
chdkptp.py.egg-info/top_level.txt
chdkptp/vendor/chdkptp/.git
chdkptp/vendor/chdkptp/COPYING
chdkptp/vendor/chdkptp/INSTALL.TXT
chdkptp/vendor/chdkptp/Makefile
chdkptp/vendor/chdkptp/README-OSX.TXT
chdkptp/vendor/chdkptp/README-RASPI-LIBS.TXT
chdkptp/vendor/chdkptp/README-RASPI.TXT
chdkptp/vendor/chdkptp/README.TXT
chdkptp/vendor/chdkptp/THANKS.TXT
chdkptp/vendor/chdkptp/USAGE.TXT
chdkptp/vendor/chdkptp/bin-snapshot.bash
chdkptp/vendor/chdkptp/bottom.mk
chdkptp/vendor/chdkptp/chdkptp-sample.sh
chdkptp/vendor/chdkptp/chdkptp.c
chdkptp/vendor/chdkptp/config-sample-linux.mk
chdkptp/vendor/chdkptp/config-sample-win32.mk
chdkptp/vendor/chdkptp/config.h
chdkptp/vendor/chdkptp/include.mk
chdkptp/vendor/chdkptp/lbuf.c
chdkptp/vendor/chdkptp/lbuf.h
chdkptp/vendor/chdkptp/libptp-endian.h
chdkptp/vendor/chdkptp/libptp-stdint.h
chdkptp/vendor/chdkptp/liveimg.c
chdkptp/vendor/chdkptp/liveimg.h
chdkptp/vendor/chdkptp/luautil.c
chdkptp/vendor/chdkptp/luautil.h
chdkptp/vendor/chdkptp/myusb.c
chdkptp/vendor/chdkptp/properties.c
chdkptp/vendor/chdkptp/ptp-pack.c
chdkptp/vendor/chdkptp/ptp.c
chdkptp/vendor/chdkptp/ptp.h
chdkptp/vendor/chdkptp/ptpcam.h
chdkptp/vendor/chdkptp/ptpip.c
chdkptp/vendor/chdkptp/rawimg.c
chdkptp/vendor/chdkptp/rawimg.h
chdkptp/vendor/chdkptp/sockutil.c
chdkptp/vendor/chdkptp/sockutil.h
chdkptp/vendor/chdkptp/chdk_headers/README.TXT
chdkptp/vendor/chdkptp/chdk_headers/core/live_view.h
chdkptp/vendor/chdkptp/chdk_headers/core/ptp.h
chdkptp/vendor/chdkptp/lfs/LICENSE
chdkptp/vendor/chdkptp/lfs/Makefile
chdkptp/vendor/chdkptp/lfs/README
chdkptp/vendor/chdkptp/lfs/lfs.c
chdkptp/vendor/chdkptp/lfs/lfs.h
chdkptp/vendor/chdkptp/lua/camtests.lua
chdkptp/vendor/chdkptp/lua/chdku.lua
chdkptp/vendor/chdkptp/lua/cli.lua
chdkptp/vendor/chdkptp/lua/dng.lua
chdkptp/vendor/chdkptp/lua/dngcli.lua
chdkptp/vendor/chdkptp/lua/errutil.lua
chdkptp/vendor/chdkptp/lua/exposure.lua
