Metadata-Version: 1.0
Name: chdkptp.py
Version: 0.1.3
Summary: Python bindings for chdkptp
Home-page: http://github.com/jbaiter/chdkptp-py.git
Author: Johannes Baiter
Author-email: johannes.baiter@gmail.com
License: GPL
Platform: UNKNOWN
